{
  "error": null,
  "data": [
    {
      "ContestantId": 0,
      "Place": 1,
      "FirstName": "Brittany",
      "LastName": "Tonozzi",
      "Hometown": "Lampasas, TX",
      "Earnings": 38428.89,
      "Event": "GB",
      "Type": "world",
      "Points": 38428.89,
      "SeasonYear": 2024,
      "StandingId": 0
    },
    {
      "ContestantId": 0,
      "Place": 2,
      "FirstName": "Andrea",
      "LastName": "Busby",
      "Hometown": "Millsap, TX",
      "Earnings": 20030.09,
      "Event": "GB",
      "Type": "world",
      "Points": 20030.09,
      "SeasonYear": 2024,
      "StandingId": 0
    },
    {
      "ContestantId": 0,
      "Place": 3,
      "FirstName": "Rachel",
      "LastName": "Huerkamp",
      "Hometown": "Delta, CO",
      "Earnings": 18460.86,
      "Event": "GB",
      "Type": "world",
      "Points": 18460.86,
      "SeasonYear": 2024,
      "StandingId": 0
    },
    {
      "ContestantId": 0,
      "Place": 4,
      "FirstName": "Karson",
      "LastName": "Berger",
      "Hometown": "Saratoga, WY",
      "Earnings": 15345.03,
      "Event": "GB",
      "Type": "world",
      "Points": 15345.03,
      "SeasonYear": 2024,
      "StandingId": 0
    },
    {
      "ContestantId": 0,
      "Place": 5,
      "FirstName": "Cheryl",
      "LastName": "Kennedy",
      "Hometown": "Bennett, CO",
      "Earnings": 15008.32,
      "Event": "GB",
      "Type": "world",
      "Points": 15008.32,
      "SeasonYear": 2024,
      "StandingId": 0
    },
    {
      "ContestantId": 0,
      "Place": 6,
      "FirstName": "Kelly",
      "LastName": "Yates",
      "Hometown": "Pueblo, CO",
      "Earnings": 12545.68,
      "Event": "GB",
      "Type": "world",
      "Points": 12545.68,
      "SeasonYear": 2024,
      "StandingId": 0
    },
    {
      "ContestantId": 0,
      "Place": 7,
      "FirstName": "Loralee",
      "LastName": "Ward",
      "Hometown": "Fort Lupton, CO",
      "Earnings": 12503.74,
      "Event": "GB",
      "Type": "world",
      "Points": 12503.74,
      "SeasonYear": 2024,
      "StandingId": 0
    },
    {
      "ContestantId": 0,
      "Place": 8,
      "FirstName": "Alex",
      "LastName": "Odle",
      "Hometown": "Brush, CO",
      "Earnings": 12169.96,
      "Event": "GB",
      "Type": "world",
      "Points": 12169.96,
      "SeasonYear": 2024,
      "StandingId": 0
    },
    {
      "ContestantId": 0,
      "Place": 9,
      "FirstName": "Sami",
      "LastName": "Buum",
      "Hometown": "Keenesburg, CO",
      "Earnings": 10924.7,
      "Event": "GB",
      "Type": "world",
      "Points": 10924.7,
      "SeasonYear": 2024,
      "StandingId": 0
    },
    {
      "ContestantId": 0,
      "Place": 10,
      "FirstName": "Taryn",
      "LastName": "Boxleitner",
      "Hometown": "Loveland, CO",
      "Earnings": 10479.41,
      "Event": "GB",
      "Type": "world",
      "Points": 10479.41,
      "SeasonYear": 2024,
      "StandingId": 0
    },
    {
      "ContestantId": 0,
      "Place": 11,
      "FirstName": "Tessa",
      "LastName": "Arnold",
      "Hometown": "Coleman, TX",
      "Earnings": 10197.4,
      "Event": "GB",
      "Type": "world",
      "Points": 10197.4,
      "SeasonYear": 2024,
      "StandingId": 0
    },
    {
      "ContestantId": 0,
      "Place": 12,
      "FirstName": "Maggie",
      "LastName": "Poloncic",
      "Hometown": "Gillette, WY",
      "Earnings": 9901.4,
      "Event": "GB",
      "Type": "world",
      "Points": 9901.4,
      "SeasonYear": 2024,
      "StandingId": 0
    },
    {
      "ContestantId": 0,
      "Place": 13,
      "FirstName": "Mackenzie",
      "LastName": "McCuistion",
      "Hometown": "Estes Park, CO",
      "Earnings": 9036.8,
      "Event": "GB",
      "Type": "world",
      "Points": 9036.8,
      "SeasonYear": 2024,
      "StandingId": 0
    },
    {
      "ContestantId": 0,
      "Place": 14,
      "FirstName": "Kim",
      "LastName": "Schulze",
      "Hometown": "Larkspur, CO",
      "Earnings": 8558.3,
      "Event": "GB",
      "Type": "world",
      "Points": 8558.3,
      "SeasonYear": 2024,
      "StandingId": 0
    },
    {
      "ContestantId": 0,
      "Place": 15,
      "FirstName": "Lake",
      "LastName": "Mehalic",
      "Hometown": "Marana, AZ",
      "Earnings": 6970.73,
      "Event": "GB",
      "Type": "world",
      "Points": 6970.73,
      "SeasonYear": 2024,
      "StandingId": 0
    },
    {
      "ContestantId": 0,
      "Place": 16,
      "FirstName": "Sage",
      "LastName": "Kohr",
      "Hometown": "Laramie, WY",
      "Earnings": 6557.58,
      "Event": "GB",
      "Type": "world",
      "Points": 6557.58,
      "SeasonYear": 2024,
      "StandingId": 0
    },
    {
      "ContestantId": 0,
      "Place": 17,
      "FirstName": "Amanda",
      "LastName": "Wisehart",
      "Hometown": "Stephenville, TX",
      "Earnings": 6032.3,
      "Event": "GB",
      "Type": "world",
      "Points": 6032.3,
      "SeasonYear": 2024,
      "StandingId": 0
    },
    {
      "ContestantId": 0,
      "Place": 18,
      "FirstName": "Laura",
      "LastName": "Lambert",
      "Hometown": "Wiggins, CO",
      "Earnings": 5657.36,
      "Event": "GB",
      "Type": "world",
      "Points": 5657.36,
      "SeasonYear": 2024,
      "StandingId": 0
    },
    {
      "ContestantId": 0,
      "Place": 19,
      "FirstName": "C.j.",
      "LastName": "Vondette",
      "Hometown": "Rifle, CO",
      "Earnings": 5532.33,
      "Event": "GB",
      "Type": "world",
      "Points": 5532.33,
      "SeasonYear": 2024,
      "StandingId": 0
    },
    {
      "ContestantId": 0,
      "Place": 20,
      "FirstName": "Emme",
      "LastName": "Norsworthy",
      "Hometown": "Thermopolis, WY",
      "Earnings": 5467.93,
      "Event": "GB",
      "Type": "world",
      "Points": 5467.93,
      "SeasonYear": 2024,
      "StandingId": 0
    },
    {
      "ContestantId": 0,
      "Place": 21,
      "FirstName": "Taylour",
      "LastName": "Latham",
      "Hometown": "Cheyenne, WY",
      "Earnings": 5395.26,
      "Event": "GB",
      "Type": "world",
      "Points": 5395.26,
      "SeasonYear": 2024,
      "StandingId": 0
    },
    {
      "ContestantId": 0,
      "Place": 22,
      "FirstName": "Katie",
      "LastName": "Ferguson",
      "Hometown": "Loveland, CO",
      "Earnings": 5347.79,
      "Event": "GB",
      "Type": "world",
      "Points": 5347.79,
      "SeasonYear": 2024,
      "StandingId": 0
    },
    {
      "ContestantId": 0,
      "Place": 23,
      "FirstName": "Shali",
      "LastName": "Lord",
      "Hometown": "Lamar, CO",
      "Earnings": 4840.08,
      "Event": "GB",
      "Type": "world",
      "Points": 4840.08,
      "SeasonYear": 2024,
      "StandingId": 0
    },
    {
      "ContestantId": 0,
      "Place": 24,
      "FirstName": "Heidi",
      "LastName": "Tillard",
      "Hometown": "Douglas, WY",
      "Earnings": 4102.42,
      "Event": "GB",
      "Type": "world",
      "Points": 4102.42,
      "SeasonYear": 2024,
      "StandingId": 0
    },
    {
      "ContestantId": 0,
      "Place": 25,
      "FirstName": "Teneille",
      "LastName": "Angland",
      "Hometown": "Grover, CO",
      "Earnings": 3326.93,
      "Event": "GB",
      "Type": "world",
      "Points": 3326.93,
      "SeasonYear": 2024,
      "StandingId": 0
    },
    {
      "ContestantId": 0,
      "Place": 26,
      "FirstName": "Chris",
      "LastName": "Gibson",
      "Hometown": "Windsor, CO",
      "Earnings": 3083.36,
      "Event": "GB",
      "Type": "world",
      "Points": 3083.36,
      "SeasonYear": 2024,
      "StandingId": 0
    },
    {
      "ContestantId": 0,
      "Place": 27,
      "FirstName": "Ronnie",
      "LastName": "Will",
      "Hometown": "Wickenburg, AZ",
      "Earnings": 2377.35,
      "Event": "GB",
      "Type": "world",
      "Points": 2377.35,
      "SeasonYear": 2024,
      "StandingId": 0
    },
    {
      "ContestantId": 0,
      "Place": 28,
      "FirstName": "Kelby",
      "LastName": "Eastman",
      "Hometown": "Pine Bluffs, WY",
      "Earnings": 2047.07,
      "Event": "GB",
      "Type": "world",
      "Points": 2047.07,
      "SeasonYear": 2024,
      "StandingId": 0
    },
    {
      "ContestantId": 0,
      "Place": 29,
      "FirstName": "Rayne",
      "LastName": "Grant",
      "Hometown": "Wheatland, WY",
      "Earnings": 2007.88,
      "Event": "GB",
      "Type": "world",
      "Points": 2007.88,
      "SeasonYear": 2024,
      "StandingId": 0
    },
    {
      "ContestantId": 0,
      "Place": 30,
      "FirstName": "Mejrusa",
      "LastName": "Rustemovic",
      "Hometown": "Kiowa, CO",
      "Earnings": 1962.16,
      "Event": "GB",
      "Type": "world",
      "Points": 1962.16,
      "SeasonYear": 2024,
      "StandingId": 0
    },
    {
      "ContestantId": 0,
      "Place": 31,
      "FirstName": "Kari",
      "LastName": "Boxleitner",
      "Hometown": "Loveland, CO",
      "Earnings": 1389.63,
      "Event": "GB",
      "Type": "world",
      "Points": 1389.63,
      "SeasonYear": 2024,
      "StandingId": 0
    },
    {
      "ContestantId": 0,
      "Place": 32,
      "FirstName": "Sydni",
      "LastName": "Blanchard",
      "Hometown": "Pueblo, CO",
      "Earnings": 1385.39,
      "Event": "GB",
      "Type": "world",
      "Points": 1385.39,
      "SeasonYear": 2024,
      "StandingId": 0
    },
    {
      "ContestantId": 0,
      "Place": 33,
      "FirstName": "Shyann",
      "LastName": "Lucas",
      "Hometown": "Jackson, WY",
      "Earnings": 1382.69,
      "Event": "GB",
      "Type": "world",
      "Points": 1382.69,
      "SeasonYear": 2024,
      "StandingId": 0
    },
    {
      "ContestantId": 0,
      "Place": 34,
      "FirstName": "Ryleigh",
      "LastName": "Hauer",
      "Hometown": "Eaton, CO",
      "Earnings": 1378.79,
      "Event": "GB",
      "Type": "world",
      "Points": 1378.79,
      "SeasonYear": 2024,
      "StandingId": 0
    },
    {
      "ContestantId": 0,
      "Place": 35,
      "FirstName": "Brittyn",
      "LastName": "Rocha",
      "Hometown": "Covington, TX",
      "Earnings": 1350.11,
      "Event": "GB",
      "Type": "world",
      "Points": 1350.11,
      "SeasonYear": 2024,
      "StandingId": 0
    },
    {
      "ContestantId": 0,
      "Place": 36,
      "FirstName": "Briana",
      "LastName": "Bailey",
      "Hometown": "Steamboat Springs, CO",
      "Earnings": 1328.23,
      "Event": "GB",
      "Type": "world",
      "Points": 1328.23,
      "SeasonYear": 2024,
      "StandingId": 0
    },
    {
      "ContestantId": 0,
      "Place": 37,
      "FirstName": "Jean",
      "LastName": "Winters",
      "Hometown": "Texline, TX",
      "Earnings": 1292.31,
      "Event": "GB",
      "Type": "world",
      "Points": 1292.31,
      "SeasonYear": 2024,
      "StandingId": 0
    },
    {
      "ContestantId": 0,
      "Place": 38,
      "FirstName": "Chandler",
      "LastName": "Camblin",
      "Hometown": "Holyoke, CO",
      "Earnings": 1109.51,
      "Event": "GB",
      "Type": "world",
      "Points": 1109.51,
      "SeasonYear": 2024,
      "StandingId": 0
    },
    {
      "ContestantId": 0,
      "Place": 39,
      "FirstName": "Annie",
      "LastName": "Campbell",
      "Hometown": "Torrington, WY",
      "Earnings": 1059.42,
      "Event": "GB",
      "Type": "world",
      "Points": 1059.42,
      "SeasonYear": 2024,
      "StandingId": 0
    },
    {
      "ContestantId": 0,
      "Place": 40,
      "FirstName": "Carley",
      "LastName": "Cervi",
      "Hometown": "Roggen, CO",
      "Earnings": 1042.27,
      "Event": "GB",
      "Type": "world",
      "Points": 1042.27,
      "SeasonYear": 2024,
      "StandingId": 0
    },
    {
      "ContestantId": 0,
      "Place": 41,
      "FirstName": "Mikala",
      "LastName": "Nealy",
      "Hometown": "Kiowa, CO",
      "Earnings": 864.47,
      "Event": "GB",
      "Type": "world",
      "Points": 864.47,
      "SeasonYear": 2024,
      "StandingId": 0
    },
    {
      "ContestantId": 0,
      "Place": 42,
      "FirstName": "Kaycee",
      "LastName": "Thomas",
      "Hometown": "Carpenter, WY",
      "Earnings": 760.87,
      "Event": "GB",
      "Type": "world",
      "Points": 760.87,
      "SeasonYear": 2024,
      "StandingId": 0
    },
    {
      "ContestantId": 0,
      "Place": 43,
      "FirstName": "Jan",
      "LastName": "Iberlin",
      "Hometown": "Buffalo, WY",
      "Earnings": 746.36,
      "Event": "GB",
      "Type": "world",
      "Points": 746.36,
      "SeasonYear": 2024,
      "StandingId": 0
    },
    {
      "ContestantId": 0,
      "Place": 44,
      "FirstName": "Taleen",
      "LastName": "Vick",
      "Hometown": "Byers, CO",
      "Earnings": 724.36,
      "Event": "GB",
      "Type": "world",
      "Points": 724.36,
      "SeasonYear": 2024,
      "StandingId": 0
    },
    {
      "ContestantId": 0,
      "Place": 45,
      "FirstName": "Jennifer",
      "LastName": "Hiler",
      "Hometown": "Greeley, CO",
      "Earnings": 687.14,
      "Event": "GB",
      "Type": "world",
      "Points": 687.14,
      "SeasonYear": 2024,
      "StandingId": 0
    },
    {
      "ContestantId": 0,
      "Place": 46,
      "FirstName": "Bailey",
      "LastName": "Rempe",
      "Hometown": "Eads, CO",
      "Earnings": 502.57,
      "Event": "GB",
      "Type": "world",
      "Points": 502.57,
      "SeasonYear": 2024,
      "StandingId": 0
    },
    {
      "ContestantId": 0,
      "Place": 47,
      "FirstName": "Shawnee",
      "LastName": "Williams",
      "Hometown": "Buffalo, WY",
      "Earnings": 411.57,
      "Event": "GB",
      "Type": "world",
      "Points": 411.57,
      "SeasonYear": 2024,
      "StandingId": 0
    },
    {
      "ContestantId": 0,
      "Place": 48,
      "FirstName": "Carrie",
      "LastName": "Sutton",
      "Hometown": "Ashby, NE",
      "Earnings": 347.42,
      "Event": "GB",
      "Type": "world",
      "Points": 347.42,
      "SeasonYear": 2024,
      "StandingId": 0
    },
    {
      "ContestantId": 0,
      "Place": 49,
      "FirstName": "Heather",
      "LastName": "Milligan",
      "Hometown": "Torrington, WY",
      "Earnings": 344.04,
      "Event": "GB",
      "Type": "world",
      "Points": 344.04,
      "SeasonYear": 2024,
      "StandingId": 0
    },
    {
      "ContestantId": 0,
      "Place": 50,
      "FirstName": "Tammy",
      "LastName": "Barnes",
      "Hometown": "Larkspur, CO",
      "Earnings": 335.43,
      "Event": "GB",
      "Type": "world",
      "Points": 335.43,
      "SeasonYear": 2024,
      "StandingId": 0
    }
  ]
}