{
  "error": null,
  "data": [
    {
      "ContestantId": 0,
      "Place": 1,
      "FirstName": "Laramie",
      "LastName": "Johnson",
      "Hometown": "Shreveport, LA",
      "Earnings": 15318.42,
      "Event": "GB",
      "Type": "world",
      "Points": 15318.42,
      "SeasonYear": 2023,
      "StandingId": 0
    },
    {
      "ContestantId": 0,
      "Place": 2,
      "FirstName": "Bethany",
      "LastName": "Ferguson",
      "Hometown": "Hopkinsville, KY",
      "Earnings": 11829.79,
      "Event": "GB",
      "Type": "world",
      "Points": 11829.79,
      "SeasonYear": 2023,
      "StandingId": 0
    },
    {
      "ContestantId": 0,
      "Place": 3,
      "FirstName": "Makayla",
      "LastName": "Purcell",
      "Hometown": "Rockledge, FL",
      "Earnings": 10860.37,
      "Event": "GB",
      "Type": "world",
      "Points": 10860.37,
      "SeasonYear": 2023,
      "StandingId": 0
    },
    {
      "ContestantId": 0,
      "Place": 4,
      "FirstName": "Traci",
      "LastName": "Ashton",
      "Hometown": "Lorida, FL",
      "Earnings": 8396.05,
      "Event": "GB",
      "Type": "world",
      "Points": 8396.05,
      "SeasonYear": 2023,
      "StandingId": 0
    },
    {
      "ContestantId": 0,
      "Place": 5,
      "FirstName": "Brooke",
      "LastName": "Ladner",
      "Hometown": "Poplarville, MS",
      "Earnings": 6659.94,
      "Event": "GB",
      "Type": "world",
      "Points": 6659.94,
      "SeasonYear": 2023,
      "StandingId": 0
    },
    {
      "ContestantId": 0,
      "Place": 6,
      "FirstName": "Ashley",
      "LastName": "Henderson",
      "Hometown": "Uriah, AL",
      "Earnings": 6378.37,
      "Event": "GB",
      "Type": "world",
      "Points": 6378.37,
      "SeasonYear": 2023,
      "StandingId": 0
    },
    {
      "ContestantId": 0,
      "Place": 7,
      "FirstName": "Kelsey",
      "LastName": "Mabry",
      "Hometown": "Piedmont, AL",
      "Earnings": 5833.18,
      "Event": "GB",
      "Type": "world",
      "Points": 5833.18,
      "SeasonYear": 2023,
      "StandingId": 0
    },
    {
      "ContestantId": 0,
      "Place": 8,
      "FirstName": "Lacey",
      "LastName": "Nail",
      "Hometown": "Okeechobee, FL",
      "Earnings": 5306.41,
      "Event": "GB",
      "Type": "world",
      "Points": 5306.41,
      "SeasonYear": 2023,
      "StandingId": 0
    },
    {
      "ContestantId": 0,
      "Place": 9,
      "FirstName": "Della",
      "LastName": "Bird",
      "Hometown": "Willston, FL",
      "Earnings": 5124.89,
      "Event": "GB",
      "Type": "world",
      "Points": 5124.89,
      "SeasonYear": 2023,
      "StandingId": 0
    },
    {
      "ContestantId": 0,
      "Place": 10,
      "FirstName": "Josey",
      "LastName": "Murphy",
      "Hometown": "Keachi, LA",
      "Earnings": 5026.8,
      "Event": "GB",
      "Type": "world",
      "Points": 5026.8,
      "SeasonYear": 2023,
      "StandingId": 0
    },
    {
      "ContestantId": 0,
      "Place": 11,
      "FirstName": "Karrigan",
      "LastName": "Cagley",
      "Hometown": "Kentwood, LA",
      "Earnings": 4521.49,
      "Event": "GB",
      "Type": "world",
      "Points": 4521.49,
      "SeasonYear": 2023,
      "StandingId": 0
    },
    {
      "ContestantId": 0,
      "Place": 12,
      "FirstName": "Tabitha",
      "LastName": "Owens",
      "Hometown": "Grady, AL",
      "Earnings": 4466.31,
      "Event": "GB",
      "Type": "world",
      "Points": 4466.31,
      "SeasonYear": 2023,
      "StandingId": 0
    },
    {
      "ContestantId": 0,
      "Place": 13,
      "FirstName": "Kayley",
      "LastName": "Kennemer",
      "Hometown": "Anderson, AL",
      "Earnings": 3868.28,
      "Event": "GB",
      "Type": "world",
      "Points": 3868.28,
      "SeasonYear": 2023,
      "StandingId": 0
    },
    {
      "ContestantId": 0,
      "Place": 14,
      "FirstName": "Hollie",
      "LastName": "Ladner",
      "Hometown": "Poplarville, MS",
      "Earnings": 2259.52,
      "Event": "GB",
      "Type": "world",
      "Points": 2259.52,
      "SeasonYear": 2023,
      "StandingId": 0
    },
    {
      "ContestantId": 0,
      "Place": 15,
      "FirstName": "Heather",
      "LastName": "McLaughlin",
      "Hometown": "Meadville, MS",
      "Earnings": 1783.05,
      "Event": "GB",
      "Type": "world",
      "Points": 1783.05,
      "SeasonYear": 2023,
      "StandingId": 0
    },
    {
      "ContestantId": 0,
      "Place": 16,
      "FirstName": "Anna",
      "LastName": "Dietrich",
      "Hometown": "Malvern, AR",
      "Earnings": 1699.11,
      "Event": "GB",
      "Type": "world",
      "Points": 1699.11,
      "SeasonYear": 2023,
      "StandingId": 0
    },
    {
      "ContestantId": 0,
      "Place": 17,
      "FirstName": "Bobbie",
      "LastName": "Alcazar",
      "Hometown": "Okeechobee, FL",
      "Earnings": 1654.16,
      "Event": "GB",
      "Type": "world",
      "Points": 1654.16,
      "SeasonYear": 2023,
      "StandingId": 0
    },
    {
      "ContestantId": 0,
      "Place": 18,
      "FirstName": "Amanda",
      "LastName": "Weekley",
      "Hometown": "Southwest Ranches, FL",
      "Earnings": 1652.52,
      "Event": "GB",
      "Type": "world",
      "Points": 1652.52,
      "SeasonYear": 2023,
      "StandingId": 0
    },
    {
      "ContestantId": 0,
      "Place": 19,
      "FirstName": "Jennifer",
      "LastName": "Hyde",
      "Hometown": "Mount Vernon, AR",
      "Earnings": 1403.89,
      "Event": "GB",
      "Type": "world",
      "Points": 1403.89,
      "SeasonYear": 2023,
      "StandingId": 0
    },
    {
      "ContestantId": 0,
      "Place": 20,
      "FirstName": "Taylor",
      "LastName": "Smith",
      "Hometown": "Fellsmere, FL",
      "Earnings": 1370.99,
      "Event": "GB",
      "Type": "world",
      "Points": 1370.99,
      "SeasonYear": 2023,
      "StandingId": 0
    },
    {
      "ContestantId": 0,
      "Place": 21,
      "FirstName": "Lindsey",
      "LastName": "Pender",
      "Hometown": "Perkinston, MS",
      "Earnings": 1355.24,
      "Event": "GB",
      "Type": "world",
      "Points": 1355.24,
      "SeasonYear": 2023,
      "StandingId": 0
    },
    {
      "ContestantId": 0,
      "Place": 22,
      "FirstName": "Addison",
      "LastName": "Roberts",
      "Hometown": "Southwest Ranches, FL",
      "Earnings": 1339.5,
      "Event": "GB",
      "Type": "world",
      "Points": 1339.5,
      "SeasonYear": 2023,
      "StandingId": 0
    },
    {
      "ContestantId": 0,
      "Place": 23,
      "FirstName": "Ajae",
      "LastName": "Griffin",
      "Hometown": "Prentiss, MS",
      "Earnings": 1128,
      "Event": "GB",
      "Type": "world",
      "Points": 1128,
      "SeasonYear": 2023,
      "StandingId": 0
    },
    {
      "ContestantId": 0,
      "Place": 24,
      "FirstName": "Rhonda",
      "LastName": "Ellison",
      "Hometown": "Calera, AL",
      "Earnings": 1046.22,
      "Event": "GB",
      "Type": "world",
      "Points": 1046.22,
      "SeasonYear": 2023,
      "StandingId": 0
    },
    {
      "ContestantId": 0,
      "Place": 25,
      "FirstName": "Jaide",
      "LastName": "Ellick",
      "Hometown": "Rogersville, AL",
      "Earnings": 950.03,
      "Event": "GB",
      "Type": "world",
      "Points": 950.03,
      "SeasonYear": 2023,
      "StandingId": 0
    },
    {
      "ContestantId": 0,
      "Place": 26,
      "FirstName": "Chloe",
      "LastName": "Frey",
      "Hometown": "Eunice, LA",
      "Earnings": 805.38,
      "Event": "GB",
      "Type": "world",
      "Points": 805.38,
      "SeasonYear": 2023,
      "StandingId": 0
    },
    {
      "ContestantId": 0,
      "Place": 27,
      "FirstName": "Christine",
      "LastName": "DeRenzo",
      "Hometown": "Reddick, FL",
      "Earnings": 776.44,
      "Event": "GB",
      "Type": "world",
      "Points": 776.44,
      "SeasonYear": 2023,
      "StandingId": 0
    },
    {
      "ContestantId": 0,
      "Place": 28,
      "FirstName": "Leann",
      "LastName": "Thomas",
      "Hometown": "Benton, AR",
      "Earnings": 486.92,
      "Event": "GB",
      "Type": "world",
      "Points": 486.92,
      "SeasonYear": 2023,
      "StandingId": 0
    },
    {
      "ContestantId": 0,
      "Place": 29,
      "FirstName": "Natasha",
      "LastName": "Stacey",
      "Hometown": "Bay Minette, AL",
      "Earnings": 481.28,
      "Event": "GB",
      "Type": "world",
      "Points": 481.28,
      "SeasonYear": 2023,
      "StandingId": 0
    },
    {
      "ContestantId": 0,
      "Place": 30,
      "FirstName": "Blythe",
      "LastName": "Odom",
      "Hometown": "Perkinston, MS",
      "Earnings": 472.58,
      "Event": "GB",
      "Type": "world",
      "Points": 472.58,
      "SeasonYear": 2023,
      "StandingId": 0
    },
    {
      "ContestantId": 0,
      "Place": 31,
      "FirstName": "Pam",
      "LastName": "Williamson",
      "Hometown": "Greenbrier, AR",
      "Earnings": 451.2,
      "Event": "GB",
      "Type": "world",
      "Points": 451.2,
      "SeasonYear": 2023,
      "StandingId": 0
    },
    {
      "ContestantId": 0,
      "Place": 32,
      "FirstName": "Kenzley",
      "LastName": "Walker",
      "Hometown": "Black Oak, AR",
      "Earnings": 189.88,
      "Event": "GB",
      "Type": "world",
      "Points": 189.88,
      "SeasonYear": 2023,
      "StandingId": 0
    },
    {
      "ContestantId": 0,
      "Place": 33,
      "FirstName": "Abby",
      "LastName": "Berry",
      "Hometown": "New Hebron, MS",
      "Earnings": 141,
      "Event": "GB",
      "Type": "world",
      "Points": 141,
      "SeasonYear": 2023,
      "StandingId": 0
    },
    {
      "ContestantId": 0,
      "Place": 34,
      "FirstName": "Kylie",
      "LastName": "Conner",
      "Hometown": "Welsh, LA",
      "Earnings": 108.57,
      "Event": "GB",
      "Type": "world",
      "Points": 108.57,
      "SeasonYear": 2023,
      "StandingId": 0
    }
  ]
}