{
  "error": null,
  "data": [
    {
      "ContestantId": 0,
      "Place": 1,
      "FirstName": "Brittany",
      "LastName": "Tonozzi",
      "Hometown": "Lampasas, TX",
      "Earnings": 496498.37,
      "Event": "GB",
      "Type": "world",
      "Points": 496498.37,
      "SeasonYear": 2023,
      "StandingId": 0
    },
    {
      "ContestantId": 0,
      "Place": 2,
      "FirstName": "Lisa",
      "LastName": "Lockhart",
      "Hometown": "Oelrichs, SD",
      "Earnings": 343687.58,
      "Event": "GB",
      "Type": "world",
      "Points": 343687.58,
      "SeasonYear": 2023,
      "StandingId": 0
    },
    {
      "ContestantId": 0,
      "Place": 3,
      "FirstName": "Kassie",
      "LastName": "Mowry",
      "Hometown": "Dublin, TX",
      "Earnings": 322592.71,
      "Event": "GB",
      "Type": "world",
      "Points": 322592.71,
      "SeasonYear": 2023,
      "StandingId": 0
    },
    {
      "ContestantId": 0,
      "Place": 4,
      "FirstName": "Jordon",
      "LastName": "Briggs",
      "Hometown": "Tolar, TX",
      "Earnings": 272518.08,
      "Event": "GB",
      "Type": "world",
      "Points": 272518.08,
      "SeasonYear": 2023,
      "StandingId": 0
    },
    {
      "ContestantId": 0,
      "Place": 5,
      "FirstName": "Emily",
      "LastName": "Beisel",
      "Hometown": "Weatherford, OK",
      "Earnings": 246674.04,
      "Event": "GB",
      "Type": "world",
      "Points": 246674.04,
      "SeasonYear": 2023,
      "StandingId": 0
    },
    {
      "ContestantId": 0,
      "Place": 6,
      "FirstName": "Sissy",
      "LastName": "Winn",
      "Hometown": "Chapman, TX",
      "Earnings": 229961.77,
      "Event": "GB",
      "Type": "world",
      "Points": 229961.77,
      "SeasonYear": 2023,
      "StandingId": 0
    },
    {
      "ContestantId": 0,
      "Place": 7,
      "FirstName": "Summer",
      "LastName": "Kosel",
      "Hometown": "Glenham, SD",
      "Earnings": 228696.65,
      "Event": "GB",
      "Type": "world",
      "Points": 228696.65,
      "SeasonYear": 2023,
      "StandingId": 0
    },
    {
      "ContestantId": 0,
      "Place": 8,
      "FirstName": "Paige",
      "LastName": "Jones",
      "Hometown": "Wayne, OK",
      "Earnings": 217138.43,
      "Event": "GB",
      "Type": "world",
      "Points": 217138.43,
      "SeasonYear": 2023,
      "StandingId": 0
    },
    {
      "ContestantId": 0,
      "Place": 9,
      "FirstName": "Jessica",
      "LastName": "Routier",
      "Hometown": "Buffalo, SD",
      "Earnings": 194842.51,
      "Event": "GB",
      "Type": "world",
      "Points": 194842.51,
      "SeasonYear": 2023,
      "StandingId": 0
    },
    {
      "ContestantId": 0,
      "Place": 10,
      "FirstName": "Stevi",
      "LastName": "Hillman",
      "Hometown": "Granbury, TX",
      "Earnings": 173989.82,
      "Event": "GB",
      "Type": "world",
      "Points": 173989.82,
      "SeasonYear": 2023,
      "StandingId": 0
    },
    {
      "ContestantId": 0,
      "Place": 11,
      "FirstName": "Hailey",
      "LastName": "Kinsel",
      "Hometown": "Cotulla, TX",
      "Earnings": 154406.41,
      "Event": "GB",
      "Type": "world",
      "Points": 154406.41,
      "SeasonYear": 2023,
      "StandingId": 0
    },
    {
      "ContestantId": 0,
      "Place": 12,
      "FirstName": "Taycie",
      "LastName": "Matthews",
      "Hometown": "Wynne, AR",
      "Earnings": 154161.4,
      "Event": "GB",
      "Type": "world",
      "Points": 154161.4,
      "SeasonYear": 2023,
      "StandingId": 0
    },
    {
      "ContestantId": 0,
      "Place": 13,
      "FirstName": "Ilyssa",
      "LastName": "Riley",
      "Hometown": "Hico, TX",
      "Earnings": 139798.15,
      "Event": "GB",
      "Type": "world",
      "Points": 139798.15,
      "SeasonYear": 2023,
      "StandingId": 0
    },
    {
      "ContestantId": 0,
      "Place": 14,
      "FirstName": "Sue",
      "LastName": "Smith",
      "Hometown": "Blackfoot, ID",
      "Earnings": 133968.73,
      "Event": "GB",
      "Type": "world",
      "Points": 133968.73,
      "SeasonYear": 2023,
      "StandingId": 0
    },
    {
      "ContestantId": 0,
      "Place": 15,
      "FirstName": "Wenda",
      "LastName": "Johnson",
      "Hometown": "Pawhuska, OK",
      "Earnings": 130505.57,
      "Event": "GB",
      "Type": "world",
      "Points": 130505.57,
      "SeasonYear": 2023,
      "StandingId": 0
    },
    {
      "ContestantId": 0,
      "Place": 16,
      "FirstName": "Sara",
      "LastName": "Winkelman",
      "Hometown": "Big Lake, MN",
      "Earnings": 91276.2,
      "Event": "GB",
      "Type": "world",
      "Points": 91276.2,
      "SeasonYear": 2023,
      "StandingId": 0
    },
    {
      "ContestantId": 0,
      "Place": 17,
      "FirstName": "Ashley",
      "LastName": "Castleberry",
      "Hometown": "Montgomery, TX",
      "Earnings": 87814.77,
      "Event": "GB",
      "Type": "world",
      "Points": 87814.77,
      "SeasonYear": 2023,
      "StandingId": 0
    },
    {
      "ContestantId": 0,
      "Place": 18,
      "FirstName": "Kelly",
      "LastName": "Allen",
      "Hometown": "Stephenville, TX",
      "Earnings": 86097.74,
      "Event": "GB",
      "Type": "world",
      "Points": 86097.74,
      "SeasonYear": 2023,
      "StandingId": 0
    },
    {
      "ContestantId": 0,
      "Place": 19,
      "FirstName": "Carlee",
      "LastName": "Otero",
      "Hometown": "Lipan, TX",
      "Earnings": 79056.3,
      "Event": "GB",
      "Type": "world",
      "Points": 79056.3,
      "SeasonYear": 2023,
      "StandingId": 0
    },
    {
      "ContestantId": 0,
      "Place": 20,
      "FirstName": "Dona",
      "LastName": "Rule",
      "Hometown": "Minco, OK",
      "Earnings": 78860.34,
      "Event": "GB",
      "Type": "world",
      "Points": 78860.34,
      "SeasonYear": 2023,
      "StandingId": 0
    },
    {
      "ContestantId": 0,
      "Place": 21,
      "FirstName": "Leslie",
      "LastName": "Smalygo",
      "Hometown": "Skiatook, OK",
      "Earnings": 74022.6,
      "Event": "GB",
      "Type": "world",
      "Points": 74022.6,
      "SeasonYear": 2023,
      "StandingId": 0
    },
    {
      "ContestantId": 0,
      "Place": 22,
      "FirstName": "Molly",
      "LastName": "Otto",
      "Hometown": "Grand Forks, ND",
      "Earnings": 72079.78,
      "Event": "GB",
      "Type": "world",
      "Points": 72079.78,
      "SeasonYear": 2023,
      "StandingId": 0
    },
    {
      "ContestantId": 0,
      "Place": 23,
      "FirstName": "Shelley",
      "LastName": "Morgan",
      "Hometown": "Eustace, TX",
      "Earnings": 68599.64,
      "Event": "GB",
      "Type": "world",
      "Points": 68599.64,
      "SeasonYear": 2023,
      "StandingId": 0
    },
    {
      "ContestantId": 0,
      "Place": 24,
      "FirstName": "Jackie",
      "LastName": "Ganter",
      "Hometown": "Abilene, TX",
      "Earnings": 67493.82,
      "Event": "GB",
      "Type": "world",
      "Points": 67493.82,
      "SeasonYear": 2023,
      "StandingId": 0
    },
    {
      "ContestantId": 0,
      "Place": 25,
      "FirstName": "Latricia",
      "LastName": "Duke",
      "Hometown": "Zephyr, TX",
      "Earnings": 55465.94,
      "Event": "GB",
      "Type": "world",
      "Points": 55465.94,
      "SeasonYear": 2023,
      "StandingId": 0
    },
    {
      "ContestantId": 0,
      "Place": 26,
      "FirstName": "Rachelle",
      "LastName": "Riggers",
      "Hometown": "Lewiston, ID",
      "Earnings": 53943.23,
      "Event": "GB",
      "Type": "world",
      "Points": 53943.23,
      "SeasonYear": 2023,
      "StandingId": 0
    },
    {
      "ContestantId": 0,
      "Place": 27,
      "FirstName": "Halyn",
      "LastName": "Lide",
      "Hometown": "China Spring, TX",
      "Earnings": 50581.37,
      "Event": "GB",
      "Type": "world",
      "Points": 50581.37,
      "SeasonYear": 2023,
      "StandingId": 0
    },
    {
      "ContestantId": 0,
      "Place": 28,
      "FirstName": "Jimmie",
      "LastName": "Smith",
      "Hometown": "McDade, TX",
      "Earnings": 50243.09,
      "Event": "GB",
      "Type": "world",
      "Points": 50243.09,
      "SeasonYear": 2023,
      "StandingId": 0
    },
    {
      "ContestantId": 0,
      "Place": 29,
      "FirstName": "Tarryn",
      "LastName": "Lee",
      "Hometown": "St. David, AZ",
      "Earnings": 48843.67,
      "Event": "GB",
      "Type": "world",
      "Points": 48843.67,
      "SeasonYear": 2023,
      "StandingId": 0
    },
    {
      "ContestantId": 0,
      "Place": 30,
      "FirstName": "Margo",
      "LastName": "Crowther",
      "Hometown": "North Fort Myers, FL",
      "Earnings": 47663.23,
      "Event": "GB",
      "Type": "world",
      "Points": 47663.23,
      "SeasonYear": 2023,
      "StandingId": 0
    },
    {
      "ContestantId": 0,
      "Place": 31,
      "FirstName": "Lynette",
      "LastName": "Brodoway",
      "Hometown": "Brooks, AB",
      "Earnings": 46406.73,
      "Event": "GB",
      "Type": "world",
      "Points": 46406.73,
      "SeasonYear": 2023,
      "StandingId": 0
    },
    {
      "ContestantId": 0,
      "Place": 32,
      "FirstName": "Hayle",
      "LastName": "Gibson",
      "Hometown": "Redcrest, CA",
      "Earnings": 46135.4,
      "Event": "GB",
      "Type": "world",
      "Points": 46135.4,
      "SeasonYear": 2023,
      "StandingId": 0
    },
    {
      "ContestantId": 0,
      "Place": 33,
      "FirstName": "Megan",
      "LastName": "McLeod-Sprague",
      "Hometown": "Marsing, ID",
      "Earnings": 45284.75,
      "Event": "GB",
      "Type": "world",
      "Points": 45284.75,
      "SeasonYear": 2023,
      "StandingId": 0
    },
    {
      "ContestantId": 0,
      "Place": 34,
      "FirstName": "Stephanie",
      "LastName": "Fryar",
      "Hometown": "Waco, TX",
      "Earnings": 44536.3,
      "Event": "GB",
      "Type": "world",
      "Points": 44536.3,
      "SeasonYear": 2023,
      "StandingId": 0
    },
    {
      "ContestantId": 0,
      "Place": 35,
      "FirstName": "Abby",
      "LastName": "Knight",
      "Hometown": "Charlo, MT",
      "Earnings": 42968.15,
      "Event": "GB",
      "Type": "world",
      "Points": 42968.15,
      "SeasonYear": 2023,
      "StandingId": 0
    },
    {
      "ContestantId": 0,
      "Place": 36,
      "FirstName": "Andrea",
      "LastName": "Busby",
      "Hometown": "Millsap, TX",
      "Earnings": 40597.97,
      "Event": "GB",
      "Type": "world",
      "Points": 40597.97,
      "SeasonYear": 2023,
      "StandingId": 0
    },
    {
      "ContestantId": 0,
      "Place": 37,
      "FirstName": "Jamie",
      "LastName": "Olsen",
      "Hometown": "Brock, TX",
      "Earnings": 40014.6,
      "Event": "GB",
      "Type": "world",
      "Points": 40014.6,
      "SeasonYear": 2023,
      "StandingId": 0
    },
    {
      "ContestantId": 0,
      "Place": 38,
      "FirstName": "Jennifer",
      "LastName": "Kalafatic",
      "Hometown": "Caldwell, ID",
      "Earnings": 36775.25,
      "Event": "GB",
      "Type": "world",
      "Points": 36775.25,
      "SeasonYear": 2023,
      "StandingId": 0
    },
    {
      "ContestantId": 0,
      "Place": 39,
      "FirstName": "Ivy",
      "LastName": "Hurst",
      "Hometown": "Springer, OK",
      "Earnings": 36635.99,
      "Event": "GB",
      "Type": "world",
      "Points": 36635.99,
      "SeasonYear": 2023,
      "StandingId": 0
    },
    {
      "ContestantId": 0,
      "Place": 40,
      "FirstName": "Erin",
      "LastName": "Wetzel",
      "Hometown": "Plant City, FL",
      "Earnings": 36008.26,
      "Event": "GB",
      "Type": "world",
      "Points": 36008.26,
      "SeasonYear": 2023,
      "StandingId": 0
    },
    {
      "ContestantId": 0,
      "Place": 41,
      "FirstName": "Keyla",
      "LastName": "Costa",
      "Hometown": "Tolar, TX",
      "Earnings": 35830.66,
      "Event": "GB",
      "Type": "world",
      "Points": 35830.66,
      "SeasonYear": 2023,
      "StandingId": 0
    },
    {
      "ContestantId": 0,
      "Place": 42,
      "FirstName": "Sharin",
      "LastName": "Hall",
      "Hometown": "Pilot Point, TX",
      "Earnings": 35765.31,
      "Event": "GB",
      "Type": "world",
      "Points": 35765.31,
      "SeasonYear": 2023,
      "StandingId": 0
    },
    {
      "ContestantId": 0,
      "Place": 43,
      "FirstName": "Bayleigh",
      "LastName": "Choate",
      "Hometown": "Fort Worth, TX",
      "Earnings": 34685.19,
      "Event": "GB",
      "Type": "world",
      "Points": 34685.19,
      "SeasonYear": 2023,
      "StandingId": 0
    },
    {
      "ContestantId": 0,
      "Place": 44,
      "FirstName": "Sarah",
      "LastName": "Waguespack",
      "Hometown": "Gonzales, LA",
      "Earnings": 33881.7,
      "Event": "GB",
      "Type": "world",
      "Points": 33881.7,
      "SeasonYear": 2023,
      "StandingId": 0
    },
    {
      "ContestantId": 0,
      "Place": 45,
      "FirstName": "Kalli",
      "LastName": "McCall",
      "Hometown": "Lufkin, TX",
      "Earnings": 33753.36,
      "Event": "GB",
      "Type": "world",
      "Points": 33753.36,
      "SeasonYear": 2023,
      "StandingId": 0
    },
    {
      "ContestantId": 0,
      "Place": 46,
      "FirstName": "Tracy",
      "LastName": "Nowlin",
      "Hometown": "Nowata, OK",
      "Earnings": 33508.99,
      "Event": "GB",
      "Type": "world",
      "Points": 33508.99,
      "SeasonYear": 2023,
      "StandingId": 0
    },
    {
      "ContestantId": 0,
      "Place": 47,
      "FirstName": "Kathy",
      "LastName": "Petska",
      "Hometown": "Turlock, CA",
      "Earnings": 33052.92,
      "Event": "GB",
      "Type": "world",
      "Points": 33052.92,
      "SeasonYear": 2023,
      "StandingId": 0
    },
    {
      "ContestantId": 0,
      "Place": 48,
      "FirstName": "Sydney",
      "LastName": "Graham",
      "Hometown": "Abilene, TX",
      "Earnings": 33016.46,
      "Event": "GB",
      "Type": "world",
      "Points": 33016.46,
      "SeasonYear": 2023,
      "StandingId": 0
    },
    {
      "ContestantId": 0,
      "Place": 49,
      "FirstName": "Abby",
      "LastName": "Pursifull",
      "Hometown": "Shreveport, LA",
      "Earnings": 32603.9,
      "Event": "GB",
      "Type": "world",
      "Points": 32603.9,
      "SeasonYear": 2023,
      "StandingId": 0
    },
    {
      "ContestantId": 0,
      "Place": 50,
      "FirstName": "Amanda",
      "LastName": "Welsh",
      "Hometown": "Stephenville, TX",
      "Earnings": 31929.03,
      "Event": "GB",
      "Type": "world",
      "Points": 31929.03,
      "SeasonYear": 2023,
      "StandingId": 0
    }
  ]
}